<?xml version="1.0" encoding="UTF-8"?>
<Sessions>
<Session>
<SessionData><SessionDate>Saturday, March 24, 2018</SessionDate>
<SessionStaticPlay>
False
</SessionStaticPlay>
</SessionData><Entries>
<Entry>
<Time>7:57:40 PM</Time>
<Data1>Gained 1 bounty</Data1>
<Data2>B1</Data2>
<Data3>L1</Data3>
</Entry>
<Entry>
<Time>7:57:41 PM</Time>
<Data1>Gained 1 bounty</Data1>
<Data2>B2</Data2>
<Data3>L1</Data3>
</Entry>
<Entry>
<Time>7:57:41 PM</Time>
<Data1>Gained 1 bounty</Data1>
<Data2>B3</Data2>
<Data3>L1</Data3>
</Entry>
<Entry>
<Time>7:57:41 PM</Time>
<Data1>Gained 1 bounty</Data1>
<Data2>B4</Data2>
<Data3>L1</Data3>
</Entry>
<Entry>
<Time>7:57:43 PM</Time>
<Data1>Gained 1 bounty</Data1>
<Data2>B5</Data2>
<Data3>L1</Data3>
</Entry>
<Entry>
<Time>7:57:43 PM</Time>
<Data1>Gained 5 bounty</Data1>
<Data2>B10</Data2>
<Data3>L1</Data3>
</Entry>
<Entry>
<Time>7:57:46 PM</Time>
<Data1>Gained 1 bounty</Data1>
<Data2>B11</Data2>
<Data3>L1</Data3>
</Entry>
<Entry>
<Time>7:57:47 PM</Time>
<Data1>Gained 1 bounty</Data1>
<Data2>B12</Data2>
<Data3>L1</Data3>
</Entry>
<Entry>
<Time>7:57:47 PM</Time>
<Data1>Gained 1 bounty</Data1>
<Data2>B13</Data2>
<Data3>L1</Data3>
</Entry>
<Entry>
<Time>7:57:48 PM</Time>
<Data1>Gained 1 bounty</Data1>
<Data2>B14</Data2>
<Data3>L1</Data3>
</Entry>
<Entry>
<Time>7:57:51 PM</Time>
<Data1>Gained 1 bounty</Data1>
<Data2>B15</Data2>
<Data3>L1</Data3>
</Entry>
<Entry>
<Time>7:57:51 PM</Time>
<Data1>Gained 5 bounty</Data1>
<Data2>B20</Data2>
<Data3>L1</Data3>
</Entry>
</Entries>
</Session>
<Entry>
<Time>7:57:51 PM</Time>
<Data1>Gained 5 bounty</Data1>
<Data2>B25</Data2>
<Data3>L1</Data3>
</Entry>
<Entry>
<Time>7:57:51 PM</Time>
<Data1>Gained 5 bounty</Data1>
<Data2>B30</Data2>
<Data3>L1</Data3>
</Entry>
<Entry>
<Time>7:57:51 PM</Time>
<Data1>Gained 5 bounty</Data1>
<Data2>B35</Data2>
<Data3>L1</Data3>
</Entry>
</Sessions>
